iiif2/iiif.py
iiif2/exc.py
iiif2/__init__.py
iiif2/web.py
iiif2-0.0.32.dist-info/DESCRIPTION.rst
iiif2-0.0.32.dist-info/METADATA
iiif2-0.0.32.dist-info/WHEEL
iiif2-0.0.32.dist-info/top_level.txt
iiif2-0.0.32.dist-info/metadata.json
iiif2-0.0.32.dist-info/RECORD
