Metadata-Version: 2.0
Name: iiif2
Version: 0.0.32
Summary: An implementation of the IIIF Image API 2.0 Specification 
Home-page: iiif.io
Author: mek
Author-email: michael.karpeles@gmail.com
License: LICENSE
Platform: any
Classifier: Development Status :: 3 - Alpha
Classifier: Environment :: Web Environment
Classifier: Intended Audience :: Developers
Classifier: License :: OSI Approved :: BSD License
Classifier: Operating System :: OS Independent
Classifier: Programming Language :: Python
Classifier: Programming Language :: Python :: 2.7
Classifier: Programming Language :: Python :: 3
Classifier: Topic :: Internet :: WWW/HTTP
Classifier: Topic :: Software Development :: Libraries :: Python Modules
Requires-Dist: Pillow (>=2.9.0)
Provides-Extra: examples
Requires-Dist: Flask (>=0.10.1); extra == 'examples'
